LICENSE.txt
MANIFEST.in
README.md
setup.py
hapi/__init__.py
hapi/base.py
hapi/blog.py
hapi/broadcast.py
hapi/error.py
hapi/forms.py
hapi/keywords.py
hapi/leads.py
hapi/logging_helper.py
hapi/nurturing.py
hapi/prospects.py
hapi/settings.py
hapi/utils.py
hapi/mixins/__init__.py
hapi/mixins/threading.py
hapipy.egg-info/PKG-INFO
hapipy.egg-info/SOURCES.txt
hapipy.egg-info/dependency_links.txt
hapipy.egg-info/requires.txt
hapipy.egg-info/top_level.txt