Metadata-Version: 1.0
Name: hapipy
Version: 2.10.0
Summary: A python wrapper around HubSpot's APIs
Home-page: https://github.com/HubSpot/hapipy
Author: HubSpot Dev Team
Author-email: devteam+hapi@hubspot.com
License: LICENSE.txt
Download-URL: https://github.com/HubSpot/hapipy/tarball/v2.10.0
Platform: UNKNOWN
